Metadata-Version: 1.0
Name: my-pizzani-package
Version: 0.1
Summary: Gaussian distribution
Home-page: UNKNOWN
Author: UNKNOWN
Author-email: UNKNOWN
License: UNKNOWN
Platform: UNKNOWN
